{
    "nodes": [
        {
            "id": "home_rayu_derlg_docs_platform_architecture_data_md",
            "label": "data.md",
            "file_type": "document",
            "source_file": "/home/rayu/DerLg/docs/platform/architecture/data.md",
            "source_location": "L1"
        },
        {
            "id": "architecture_data_data_architecture",
            "label": "Data Architecture",
            "file_type": "document",
            "source_file": "/home/rayu/DerLg/docs/platform/architecture/data.md",
            "source_location": "L1"
        },
        {
            "id": "architecture_data_primary_database_postgresql_supabase",
            "label": "Primary Database \u2014 PostgreSQL (Supabase)",
            "file_type": "document",
            "source_file": "/home/rayu/DerLg/docs/platform/architecture/data.md",
            "source_location": "L7"
        },
        {
            "id": "architecture_data_hosting_strategy",
            "label": "Hosting Strategy",
            "file_type": "document",
            "source_file": "/home/rayu/DerLg/docs/platform/architecture/data.md",
            "source_location": "L17"
        },
        {
            "id": "architecture_data_orm_migration_strategy",
            "label": "ORM & Migration Strategy",
            "file_type": "document",
            "source_file": "/home/rayu/DerLg/docs/platform/architecture/data.md",
            "source_location": "L23"
        },
        {
            "id": "architecture_data_row_level_security_rls",
            "label": "Row-Level Security (RLS)",
            "file_type": "document",
            "source_file": "/home/rayu/DerLg/docs/platform/architecture/data.md",
            "source_location": "L32"
        },
        {
            "id": "architecture_data_cache_sessions_redis",
            "label": "Cache & Sessions \u2014 Redis",
            "file_type": "document",
            "source_file": "/home/rayu/DerLg/docs/platform/architecture/data.md",
            "source_location": "L40"
        },
        {
            "id": "architecture_data_key_patterns_ttl_policies",
            "label": "Key Patterns & TTL Policies",
            "file_type": "document",
            "source_file": "/home/rayu/DerLg/docs/platform/architecture/data.md",
            "source_location": "L49"
        },
        {
            "id": "architecture_data_pub_sub_channels",
            "label": "Pub / Sub Channels",
            "file_type": "document",
            "source_file": "/home/rayu/DerLg/docs/platform/architecture/data.md",
            "source_location": "L59"
        },
        {
            "id": "architecture_data_file_storage_supabase_storage",
            "label": "File Storage \u2014 Supabase Storage",
            "file_type": "document",
            "source_file": "/home/rayu/DerLg/docs/platform/architecture/data.md",
            "source_location": "L68"
        },
        {
            "id": "architecture_data_buckets_access_patterns",
            "label": "Buckets & Access Patterns",
            "file_type": "document",
            "source_file": "/home/rayu/DerLg/docs/platform/architecture/data.md",
            "source_location": "L76"
        },
        {
            "id": "architecture_data_upload_flow",
            "label": "Upload Flow",
            "file_type": "document",
            "source_file": "/home/rayu/DerLg/docs/platform/architecture/data.md",
            "source_location": "L84"
        },
        {
            "id": "architecture_data_data_flow_diagrams",
            "label": "Data Flow Diagrams",
            "file_type": "document",
            "source_file": "/home/rayu/DerLg/docs/platform/architecture/data.md",
            "source_location": "L93"
        },
        {
            "id": "architecture_data_read_flow",
            "label": "Read Flow",
            "file_type": "document",
            "source_file": "/home/rayu/DerLg/docs/platform/architecture/data.md",
            "source_location": "L95"
        },
        {
            "id": "architecture_data_codeblock_1",
            "label": "code:mermaid (sequenceDiagram)",
            "file_type": "document",
            "source_file": "/home/rayu/DerLg/docs/platform/architecture/data.md",
            "source_location": "L97"
        },
        {
            "id": "architecture_data_write_flow",
            "label": "Write Flow",
            "file_type": "document",
            "source_file": "/home/rayu/DerLg/docs/platform/architecture/data.md",
            "source_location": "L119"
        },
        {
            "id": "architecture_data_codeblock_2",
            "label": "code:mermaid (sequenceDiagram)",
            "file_type": "document",
            "source_file": "/home/rayu/DerLg/docs/platform/architecture/data.md",
            "source_location": "L121"
        },
        {
            "id": "architecture_data_ai_flow",
            "label": "AI Flow",
            "file_type": "document",
            "source_file": "/home/rayu/DerLg/docs/platform/architecture/data.md",
            "source_location": "L140"
        },
        {
            "id": "architecture_data_codeblock_3",
            "label": "code:mermaid (sequenceDiagram)",
            "file_type": "document",
            "source_file": "/home/rayu/DerLg/docs/platform/architecture/data.md",
            "source_location": "L142"
        },
        {
            "id": "architecture_data_data_ownership_rules",
            "label": "Data Ownership Rules",
            "file_type": "document",
            "source_file": "/home/rayu/DerLg/docs/platform/architecture/data.md",
            "source_location": "L171"
        }
    ],
    "edges": [
        {
            "source": "home_rayu_derlg_docs_platform_architecture_data_md",
            "target": "architecture_data_data_architecture",
            "relation": "contains",
            "confidence": "EXTRACTED",
            "source_file": "/home/rayu/DerLg/docs/platform/architecture/data.md",
            "source_location": "L1",
            "weight": 1.0
        },
        {
            "source": "architecture_data_data_architecture",
            "target": "architecture_data_primary_database_postgresql_supabase",
            "relation": "contains",
            "confidence": "EXTRACTED",
            "source_file": "/home/rayu/DerLg/docs/platform/architecture/data.md",
            "source_location": "L7",
            "weight": 1.0
        },
        {
            "source": "architecture_data_primary_database_postgresql_supabase",
            "target": "architecture_data_hosting_strategy",
            "relation": "contains",
            "confidence": "EXTRACTED",
            "source_file": "/home/rayu/DerLg/docs/platform/architecture/data.md",
            "source_location": "L17",
            "weight": 1.0
        },
        {
            "source": "architecture_data_primary_database_postgresql_supabase",
            "target": "architecture_data_orm_migration_strategy",
            "relation": "contains",
            "confidence": "EXTRACTED",
            "source_file": "/home/rayu/DerLg/docs/platform/architecture/data.md",
            "source_location": "L23",
            "weight": 1.0
        },
        {
            "source": "architecture_data_primary_database_postgresql_supabase",
            "target": "architecture_data_row_level_security_rls",
            "relation": "contains",
            "confidence": "EXTRACTED",
            "source_file": "/home/rayu/DerLg/docs/platform/architecture/data.md",
            "source_location": "L32",
            "weight": 1.0
        },
        {
            "source": "architecture_data_data_architecture",
            "target": "architecture_data_cache_sessions_redis",
            "relation": "contains",
            "confidence": "EXTRACTED",
            "source_file": "/home/rayu/DerLg/docs/platform/architecture/data.md",
            "source_location": "L40",
            "weight": 1.0
        },
        {
            "source": "architecture_data_cache_sessions_redis",
            "target": "architecture_data_key_patterns_ttl_policies",
            "relation": "contains",
            "confidence": "EXTRACTED",
            "source_file": "/home/rayu/DerLg/docs/platform/architecture/data.md",
            "source_location": "L49",
            "weight": 1.0
        },
        {
            "source": "architecture_data_cache_sessions_redis",
            "target": "architecture_data_pub_sub_channels",
            "relation": "contains",
            "confidence": "EXTRACTED",
            "source_file": "/home/rayu/DerLg/docs/platform/architecture/data.md",
            "source_location": "L59",
            "weight": 1.0
        },
        {
            "source": "architecture_data_data_architecture",
            "target": "architecture_data_file_storage_supabase_storage",
            "relation": "contains",
            "confidence": "EXTRACTED",
            "source_file": "/home/rayu/DerLg/docs/platform/architecture/data.md",
            "source_location": "L68",
            "weight": 1.0
        },
        {
            "source": "architecture_data_file_storage_supabase_storage",
            "target": "architecture_data_buckets_access_patterns",
            "relation": "contains",
            "confidence": "EXTRACTED",
            "source_file": "/home/rayu/DerLg/docs/platform/architecture/data.md",
            "source_location": "L76",
            "weight": 1.0
        },
        {
            "source": "architecture_data_file_storage_supabase_storage",
            "target": "architecture_data_upload_flow",
            "relation": "contains",
            "confidence": "EXTRACTED",
            "source_file": "/home/rayu/DerLg/docs/platform/architecture/data.md",
            "source_location": "L84",
            "weight": 1.0
        },
        {
            "source": "architecture_data_data_architecture",
            "target": "architecture_data_data_flow_diagrams",
            "relation": "contains",
            "confidence": "EXTRACTED",
            "source_file": "/home/rayu/DerLg/docs/platform/architecture/data.md",
            "source_location": "L93",
            "weight": 1.0
        },
        {
            "source": "architecture_data_data_flow_diagrams",
            "target": "architecture_data_read_flow",
            "relation": "contains",
            "confidence": "EXTRACTED",
            "source_file": "/home/rayu/DerLg/docs/platform/architecture/data.md",
            "source_location": "L95",
            "weight": 1.0
        },
        {
            "source": "architecture_data_read_flow",
            "target": "architecture_data_codeblock_1",
            "relation": "contains",
            "confidence": "EXTRACTED",
            "source_file": "/home/rayu/DerLg/docs/platform/architecture/data.md",
            "source_location": "L97",
            "weight": 1.0
        },
        {
            "source": "architecture_data_data_flow_diagrams",
            "target": "architecture_data_write_flow",
            "relation": "contains",
            "confidence": "EXTRACTED",
            "source_file": "/home/rayu/DerLg/docs/platform/architecture/data.md",
            "source_location": "L119",
            "weight": 1.0
        },
        {
            "source": "architecture_data_write_flow",
            "target": "architecture_data_codeblock_2",
            "relation": "contains",
            "confidence": "EXTRACTED",
            "source_file": "/home/rayu/DerLg/docs/platform/architecture/data.md",
            "source_location": "L121",
            "weight": 1.0
        },
        {
            "source": "architecture_data_data_flow_diagrams",
            "target": "architecture_data_ai_flow",
            "relation": "contains",
            "confidence": "EXTRACTED",
            "source_file": "/home/rayu/DerLg/docs/platform/architecture/data.md",
            "source_location": "L140",
            "weight": 1.0
        },
        {
            "source": "architecture_data_ai_flow",
            "target": "architecture_data_codeblock_3",
            "relation": "contains",
            "confidence": "EXTRACTED",
            "source_file": "/home/rayu/DerLg/docs/platform/architecture/data.md",
            "source_location": "L142",
            "weight": 1.0
        },
        {
            "source": "architecture_data_data_architecture",
            "target": "architecture_data_data_ownership_rules",
            "relation": "contains",
            "confidence": "EXTRACTED",
            "source_file": "/home/rayu/DerLg/docs/platform/architecture/data.md",
            "source_location": "L171",
            "weight": 1.0
        }
    ],
    "input_tokens": 0,
    "output_tokens": 0
}